kelvin/sdk/pubsub/__init__.py
kelvin/sdk/pubsub/client.py
kelvin/sdk/pubsub/config.py
kelvin/sdk/pubsub/connection.py
kelvin/sdk/pubsub/error.py
kelvin/sdk/pubsub/prometheus.py
kelvin/sdk/pubsub/py.typed
kelvin/sdk/pubsub/types.py
kelvin/sdk/pubsub/utils.py
kelvin/sdk/pubsub/version.py
kelvin_sdk_pubsub-3.0.5.dist-info/METADATA
kelvin_sdk_pubsub-3.0.5.dist-info/WHEEL
kelvin_sdk_pubsub-3.0.5.dist-info/top_level.txt
kelvin_sdk_pubsub-3.0.5.dist-info/RECORD
